gutenTAG/__init__.py
gutenTAG/__main__.py
gutenTAG/_version.py
gutenTAG/consolidator.py
gutenTAG/gutenTAG.py
gutenTAG/py.typed
gutenTAG/timeseries.py
gutenTAG/addons/__init__.py
gutenTAG/addons/builtin.py
gutenTAG/addons/timeeval.py
gutenTAG/anomalies/__init__.py
gutenTAG/anomalies/types/__init__.py
gutenTAG/anomalies/types/amplitude.py
gutenTAG/anomalies/types/extremum.py
gutenTAG/anomalies/types/frequency.py
gutenTAG/anomalies/types/kind.py
gutenTAG/anomalies/types/mean.py
gutenTAG/anomalies/types/mode_correlation.py
gutenTAG/anomalies/types/pattern.py
gutenTAG/anomalies/types/pattern_shift.py
gutenTAG/anomalies/types/platform.py
gutenTAG/anomalies/types/trend.py
gutenTAG/anomalies/types/variance.py
gutenTAG/api/__init__.py
gutenTAG/api/bo.py
gutenTAG/base_oscillations/__init__.py
gutenTAG/base_oscillations/base_oscillation.py
gutenTAG/base_oscillations/cosine.py
gutenTAG/base_oscillations/custom_input.py
gutenTAG/base_oscillations/cylinder_bell_funnel.py
gutenTAG/base_oscillations/dirichlet.py
gutenTAG/base_oscillations/ecg.py
gutenTAG/base_oscillations/formula.py
gutenTAG/base_oscillations/interface.py
gutenTAG/base_oscillations/mls.py
gutenTAG/base_oscillations/polynomial.py
gutenTAG/base_oscillations/random_mode_jump.py
gutenTAG/base_oscillations/random_walk.py
gutenTAG/base_oscillations/sawtooth.py
gutenTAG/base_oscillations/sine.py
gutenTAG/base_oscillations/square.py
gutenTAG/base_oscillations/utils/__init__.py
gutenTAG/base_oscillations/utils/math_func_support.py
gutenTAG/config/__init__.py
gutenTAG/config/parser.py
gutenTAG/config/schema_loader.py
gutenTAG/config/validator.py
gutenTAG/config/schema/__init__.py
gutenTAG/config/schema/anomaly-kind.guten-tag-generation-config.schema.yaml
gutenTAG/config/schema/anomaly.guten-tag-generation-config.schema.yaml
gutenTAG/config/schema/formula.guten-tag-generation-config.schema.yaml
gutenTAG/config/schema/guten-tag-generation-config.schema.yaml
timeeval_gutentag-1.5.0.dist-info/licenses/LICENSE
timeeval_gutentag-1.5.0.dist-info/METADATA
timeeval_gutentag-1.5.0.dist-info/WHEEL
timeeval_gutentag-1.5.0.dist-info/entry_points.txt
timeeval_gutentag-1.5.0.dist-info/top_level.txt
timeeval_gutentag-1.5.0.dist-info/RECORD
