Metadata-Version: 2.4
Name: timeeval-GutenTAG
Version: 1.5.0
Summary: A good Timeseries Anomaly Generator.
Home-page: https://github.com/TimeEval/gutentag
Author-email: Phillip Wenig <phillip.wenig@hpi.de>, Sebastian Schmidl <sebastian.schmidl@hpi.de>
License-Expression: MIT
Classifier: Programming Language :: Python
Classifier: Programming Language :: Python :: 3
Classifier: Programming Language :: Python :: 3.9
Classifier: Programming Language :: Python :: 3.10
Classifier: Programming Language :: Python :: 3.11
Classifier: Programming Language :: Python :: 3.12
Classifier: Programming Language :: Python :: 3.13
Classifier: Typing :: Typed
Classifier: Topic :: Software Development
Classifier: Topic :: Scientific/Engineering
Classifier: Intended Audience :: Science/Research
Classifier: Intended Audience :: Developers
Requires-Python: <3.14,>=3.9
License-File: LICENSE
Requires-Dist: numpy>=1.25.0
Requires-Dist: pandas>=1.3.0
Requires-Dist: scipy<1.15,>=1.7.3
Requires-Dist: scikit-learn>=1.0.0
Requires-Dist: matplotlib>=3.5.0
Requires-Dist: pyyaml>=6.0
Requires-Dist: tqdm>=4.54.0
Requires-Dist: joblib>=1.2.0
Requires-Dist: gitpython>=3.1.0
Requires-Dist: neurokit2==0.1.2
Requires-Dist: jsonschema>=4.4.0
Provides-Extra: dev
Requires-Dist: pytest; extra == "dev"
Requires-Dist: pytest-cov; extra == "dev"
Requires-Dist: freezegun; extra == "dev"
Requires-Dist: mypy==1.15.0; extra == "dev"
Requires-Dist: flake8==7.2.0; extra == "dev"
Requires-Dist: black==25.1.0; extra == "dev"
Requires-Dist: pre-commit; extra == "dev"
Requires-Dist: types-PyYAML; extra == "dev"
Requires-Dist: types-jsonschema; extra == "dev"
Dynamic: description
Dynamic: description-content-type
Dynamic: home-page
Dynamic: license-file
